projectlens/__init__.py
projectlens/cli.py
projectlens/core.py
projectlens/utils.py
projectlens/configs/.projectignore
projectlens/configs/__init__.py
projectlens/configs/config.py
projectlens-0.1.2.dist-info/METADATA
projectlens-0.1.2.dist-info/WHEEL
projectlens-0.1.2.dist-info/entry_points.txt
projectlens-0.1.2.dist-info/licenses/LICENSE
projectlens-0.1.2.dist-info/RECORD
