Metadata-Version: 2.4
Name: projectlens
Version: 0.1.2
Summary: A tool for collecting and analyzing Python project files for LLM optimization
Project-URL: Repository, https://github.com/cmcouto-silva/projectlens
Project-URL: Documentation, https://projectlens.readthedocs.io
Project-URL: Donate, https://buymeacoffee.com/cmcoutosilva
Project-URL: Issues, https://github.com/cmcouto-silva/projectlens/issues
Author-email: Cainã Max Couto da Silva <cmcouto.silva@gmail.com>
License-Expression: MIT
License-File: LICENSE
Keywords: ai,code,development,llm,project
Classifier: Development Status :: 5 - Production/Stable
Classifier: Intended Audience :: Developers
Classifier: License :: OSI Approved :: MIT License
Classifier: Programming Language :: Python :: 3
Classifier: Programming Language :: Python :: 3.9
Classifier: Programming Language :: Python :: 3.10
Classifier: Programming Language :: Python :: 3.11
Classifier: Programming Language :: Python :: 3.12
Classifier: Programming Language :: Python :: 3.13
Requires-Python: >=3.9
